setup.py
vm_distributions/Binomialdistribution.py
vm_distributions/Gaussiandistribution.py
vm_distributions/Generaldistribution.py
vm_distributions/__init__.py
vm_distributions.egg-info/PKG-INFO
vm_distributions.egg-info/SOURCES.txt
vm_distributions.egg-info/dependency_links.txt
vm_distributions.egg-info/not-zip-safe
vm_distributions.egg-info/top_level.txt