Metadata-Version: 1.0
Name: vm-distributions
Version: 1.1
Summary: Gaussian distributions
Home-page: UNKNOWN
Author: Vishal Madheshia
Author-email: vishalmadheshia@gmail.com
License: UNKNOWN
Platform: UNKNOWN
